{
  "_class": "group",
  "booleanOperation": -1,
  "clippingMaskMode": 0,
  "do_objectID": "8B8EA7F1-7F97-46D3-B566-8F0785738A10",
  "exportOptions": {
    "_class": "exportOptions",
    "do_objectID": "E714C5B1-A297-4E4E-B011-2EC08379D545",
    "exportFormats": [
    ],
    "includedLayerIds": [
    ],
    "layerOptions": 0,
    "shouldTrim": false
  },
  "frame": {
    "_class": "rect",
    "constrainProportions": false,
    "do_objectID": "B9B7E8CB-23FF-4706-ADDB-CF208D22B7D0",
    "height": 70,
    "width": 394,
    "x": 82,
    "y": 1148
  },
  "hasClickThrough": false,
  "hasClippingMask": false,
  "isFixedToViewport": false,
  "isFlippedHorizontal": false,
  "isFlippedVertical": false,
  "isLocked": false,
  "isVisible": true,
  "layerListExpandedType": 2,
  "layers": [
    {
      "class": "text",
      "id": "8601110F-6B3B-46F7-ADAC-0619019DA307"
    }
  ],
  "name": "Group 8 Copy",
  "nameIsFixed": false,
  "resizingConstraint": 63,
  "resizingType": 0,
  "rotation": 0,
  "shouldBreakMaskChain": false,
  "style": {
    "_class": "style",
    "do_objectID": "FC337874-EA26-4649-A478-9202CB3611FE",
    "endMarkerType": 0,
    "miterLimit": 10,
    "startMarkerType": 0,
    "windingRule": 1
  }
}