{
  "_class": "text",
  "attributedString": {
    "_class": "attributedString",
    "attributes": [
      {
        "_class": "stringAttribute",
        "attributes": {
          "MSAttributedStringColorAttribute": {
            "_class": "color",
            "alpha": 1,
            "blue": 0.2543048469387755,
            "green": 0.2310909003086912,
            "red": 0.217825787948643
          },
          "MSAttributedStringFontAttribute": {
            "_class": "fontDescriptor",
            "attributes": {
              "name": "Avenir-Heavy",
              "size": 12
            }
          },
          "kerning": 0.2000000029802322,
          "paragraphStyle": {
            "_class": "paragraphStyle",
            "alignment": 0,
            "allowsDefaultTighteningForTruncation": 0,
            "maximumLineHeight": 16,
            "minimumLineHeight": 16
          }
        },
        "length": 18,
        "location": 0
      }
    ],
    "string": "King James Digital"
  },
  "automaticallyDrawOnUnderlyingPath": false,
  "booleanOperation": 0,
  "clippingMaskMode": 0,
  "do_objectID": "B9A84F30-E5E7-4DB7-9154-127A6563D5F6",
  "dontSynchroniseWithSymbol": false,
  "exportOptions": {
    "_class": "exportOptions",
    "do_objectID": "CF750A80-4D9B-4958-A556-8A2F0F7CF530",
    "exportFormats": [
    ],
    "includedLayerIds": [
    ],
    "layerOptions": 0,
    "shouldTrim": false
  },
  "frame": {
    "_class": "rect",
    "constrainProportions": false,
    "do_objectID": "CB4C634C-50DA-4FCD-8F16-C503EC3515B0",
    "height": 16,
    "width": 109,
    "x": 38,
    "y": 272
  },
  "glyphBounds": "{{0, 2}, {108, 13}}",
  "hasClippingMask": false,
  "isFixedToViewport": false,
  "isFlippedHorizontal": false,
  "isFlippedVertical": false,
  "isLocked": false,
  "isVisible": true,
  "layerListExpandedType": 0,
  "lineSpacingBehaviour": 2,
  "name": "King James Digital",
  "nameIsFixed": false,
  "resizingConstraint": 11,
  "resizingType": 0,
  "rotation": 0,
  "sharedStyleID": "9202282B-B101-4ED1-80C6-C3A7BB709B69",
  "shouldBreakMaskChain": false,
  "style": {
    "_class": "style",
    "do_objectID": "2CF6DCD7-3886-4C71-B3C4-B40E26AA9295",
    "endMarkerType": 0,
    "miterLimit": 10,
    "startMarkerType": 0,
    "textStyle": {
      "_class": "textStyle",
      "do_objectID": "477FE2E0-25BA-4F5D-A602-C2C006654E7D",
      "encodedAttributes": {
        "MSAttributedStringColorAttribute": {
          "_class": "color",
          "alpha": 1,
          "blue": 0.2543048469387755,
          "green": 0.2310909003086912,
          "red": 0.217825787948643
        },
        "MSAttributedStringFontAttribute": {
          "_class": "fontDescriptor",
          "attributes": {
            "name": "Avenir-Heavy",
            "size": 12
          }
        },
        "kerning": 0.2000000029802322,
        "paragraphStyle": {
          "_class": "paragraphStyle",
          "alignment": 0,
          "allowsDefaultTighteningForTruncation": 0,
          "maximumLineHeight": 16,
          "minimumLineHeight": 16
        }
      },
      "verticalAlignment": 0
    },
    "windingRule": 1
  },
  "textBehaviour": 0
}