{
  "_class": "group",
  "booleanOperation": -1,
  "clippingMaskMode": 0,
  "do_objectID": "EE3896B7-FA5C-4E5F-ACCE-F7DAD20ED39F",
  "exportOptions": {
    "_class": "exportOptions",
    "do_objectID": "2F3B20F0-5FF2-4696-9ADF-A179B965B483",
    "exportFormats": [
    ],
    "includedLayerIds": [
    ],
    "layerOptions": 0,
    "shouldTrim": false
  },
  "frame": {
    "_class": "rect",
    "constrainProportions": false,
    "do_objectID": "1D6C6499-FB28-47F6-B376-678A69B60C70",
    "height": 849.9999999999978,
    "width": 237.0000000000002,
    "x": 0,
    "y": 0
  },
  "hasClickThrough": false,
  "hasClippingMask": false,
  "isFixedToViewport": false,
  "isFlippedHorizontal": false,
  "isFlippedVertical": false,
  "isLocked": false,
  "isVisible": true,
  "layerListExpandedType": 2,
  "layers": [
    {
      "class": "rectangle",
      "id": "4533EBF1-ECED-4B65-AA14-8694D2D24685"
    }
  ],
  "name": "container/rounded/fill",
  "nameIsFixed": false,
  "resizingConstraint": 63,
  "resizingType": 0,
  "rotation": 0,
  "shouldBreakMaskChain": false,
  "style": {
    "_class": "style",
    "do_objectID": "6A3E5629-F266-4BC6-AD16-CC6272ED5FFB",
    "endMarkerType": 0,
    "miterLimit": 10,
    "startMarkerType": 0,
    "windingRule": 1
  }
}