{
  "_class": "symbolInstance",
  "booleanOperation": 0,
  "clippingMaskMode": 0,
  "do_objectID": "9B69FE32-5C5A-4815-80A0-0D894A65FEEE",
  "exportOptions": {
    "_class": "exportOptions",
    "do_objectID": "8A1880C5-A168-4711-8E21-5F1895B2B035",
    "exportFormats": [
    ],
    "includedLayerIds": [
    ],
    "layerOptions": 0,
    "shouldTrim": false
  },
  "frame": {
    "_class": "rect",
    "constrainProportions": false,
    "do_objectID": "22EEE856-5E92-4ACB-88F4-9DE79DF2135C",
    "height": 314,
    "width": 322,
    "x": 701,
    "y": 1035
  },
  "hasClippingMask": false,
  "horizontalSpacing": 0,
  "isFixedToViewport": false,
  "isFlippedHorizontal": false,
  "isFlippedVertical": false,
  "isLocked": false,
  "isVisible": true,
  "layerListExpandedType": 0,
  "name": "container/rounded/fill copy 6",
  "nameIsFixed": false,
  "overrideValues": [
  ],
  "resizingConstraint": 63,
  "resizingType": 0,
  "rotation": 0,
  "scale": 1,
  "shouldBreakMaskChain": false,
  "style": {
    "_class": "style",
    "do_objectID": "B3390C36-FF36-4CF2-873B-1D2E689FCB76",
    "endMarkerType": 0,
    "miterLimit": 10,
    "startMarkerType": 0,
    "windingRule": 1
  },
  "symbolID": "E6B8E08D-9285-4205-B764-FA6C61B306B7",
  "verticalSpacing": 0
}