{
  "_class": "shapePath",
  "booleanOperation": -1,
  "clippingMaskMode": 0,
  "do_objectID": "8FBA9ECC-926B-4F65-B83F-6C9759A70266",
  "edited": true,
  "exportOptions": {
    "_class": "exportOptions",
    "do_objectID": "4C818BE4-3DB6-49C9-8951-C0467B4E85E9",
    "exportFormats": [
    ],
    "includedLayerIds": [
    ],
    "layerOptions": 0,
    "shouldTrim": false
  },
  "frame": {
    "_class": "rect",
    "constrainProportions": false,
    "do_objectID": "0678E8A3-E113-4984-88E4-CAEF50F00D9B",
    "height": 2,
    "width": 28,
    "x": 126,
    "y": 54
  },
  "hasClippingMask": false,
  "isClosed": false,
  "isFixedToViewport": false,
  "isFlippedHorizontal": false,
  "isFlippedVertical": false,
  "isLocked": false,
  "isVisible": true,
  "layerListExpandedType": 0,
  "name": "Line 3 Copy 19",
  "nameIsFixed": false,
  "pointRadiusBehaviour": 1,
  "points": [
    {
      "_class": "curvePoint",
      "cornerRadius": 0,
      "curveFrom": "{-8.7678571428571441, 0.49999999999999845}",
      "curveMode": 1,
      "curveTo": "{-8.7678571428571441, 0.49999999999999845}",
      "hasCurveFrom": false,
      "hasCurveTo": false,
      "point": "{0.0030691964285876681, 0.49999999999999978}"
    },
    {
      "_class": "curvePoint",
      "cornerRadius": 0,
      "curveFrom": "{-8.7678571428571441, 0.49999999999999845}",
      "curveMode": 1,
      "curveTo": "{-8.7678571428571441, 0.49999999999999845}",
      "hasCurveFrom": false,
      "hasCurveTo": false,
      "point": "{0.98224748883927759, 0.5}"
    }
  ],
  "resizingConstraint": 63,
  "resizingType": 0,
  "rotation": 0,
  "shouldBreakMaskChain": false,
  "style": {
    "_class": "style",
    "borderOptions": {
      "_class": "borderOptions",
      "dashPattern": [
      ],
      "do_objectID": "43DA06DD-14F7-4E34-A5C5-E39329F9FF26",
      "isEnabled": false,
      "lineCapStyle": 2,
      "lineJoinStyle": 0
    },
    "borders": [
      {
        "_class": "border",
        "color": {
          "_class": "color",
          "alpha": 1,
          "blue": 0.2543048469387755,
          "green": 0.2310909003086912,
          "red": 0.217825787948643
        },
        "fillType": 0,
        "isEnabled": true,
        "position": 0,
        "thickness": 1
      }
    ],
    "do_objectID": "A4E7F1D2-3255-4BB5-81A2-0ADBE747C671",
    "endMarkerType": 0,
    "fills": [
      {
        "_class": "fill",
        "color": {
          "_class": "color",
          "alpha": 1,
          "blue": 0.847,
          "green": 0.847,
          "red": 0.847
        },
        "fillType": 0,
        "isEnabled": false,
        "noiseIndex": 0,
        "noiseIntensity": 0,
        "patternFillType": 1,
        "patternTileScale": 1
      }
    ],
    "miterLimit": 10,
    "startMarkerType": 0,
    "windingRule": 1
  }
}